postmanager/__init__.py
postmanager/config.py
postmanager/exception.py
postmanager/http.py
postmanager/manager.py
postmanager/media_data.py
postmanager/meta_data.py
postmanager/post.py
postmanager/py.typed
postmanager/storage_adapter.py
postmanager/storage_proxy_local.py
postmanager/storage_proxy_s3.py
postmanager/cli/__init__.py
postmanager/cli/main.py
postmanager/interfaces/__init__.py
postmanager/interfaces/storage_interface.py
postmanager/interfaces/storage_proxy.py
postmanager-0.1.6.dist-info/LICENSE
postmanager-0.1.6.dist-info/METADATA
postmanager-0.1.6.dist-info/WHEEL
postmanager-0.1.6.dist-info/entry_points.txt
postmanager-0.1.6.dist-info/top_level.txt
postmanager-0.1.6.dist-info/RECORD
