Metadata-Version: 2.1
Name: postmanager
Version: 0.1.6
Summary: Post manager to manage all post types with various storage backends
Home-page: https://subaquatic-pierre.github.io/postmanager
Author: Pierre du Toit
Author-email: subaquatic.pierre@gmail.com
License: MIT
Project-URL: Source, https://github.com/subaquatic-pierre/postmanager
Project-URL: Tracker, https://github.com/alexmalins/subaquatic-pierre/postmanager/issues
Project-URL: Documentation, https://subaquatic-pierre.github.io/postmanager
Platform: unix
Platform: linux
Platform: osx
Platform: cygwin
Platform: win32
Classifier: Programming Language :: Python :: 3.9
Classifier: License :: OSI Approved :: MIT License
Classifier: Operating System :: OS Independent
Requires-Python: <4,>=3.7
License-File: LICENSE
Requires-Dist: boto3
Provides-Extra: testing
Requires-Dist: pytest (>=6.0) ; extra == 'testing'
Requires-Dist: coverage (==4.4.1) ; extra == 'testing'
Requires-Dist: mypy (>=0.910) ; extra == 'testing'
Requires-Dist: flake8 (>=3.9) ; extra == 'testing'
Requires-Dist: tox (>=3.24) ; extra == 'testing'
